mediaflow_proxy/__init__.py
mediaflow_proxy/configs.py
mediaflow_proxy/const.py
mediaflow_proxy/handlers.py
mediaflow_proxy/main.py
mediaflow_proxy/middleware.py
mediaflow_proxy/mpd_processor.py
mediaflow_proxy/schemas.py
mediaflow_proxy/drm/__init__.py
mediaflow_proxy/drm/decrypter.py
mediaflow_proxy/extractors/F16Px.py
mediaflow_proxy/extractors/__init__.py
mediaflow_proxy/extractors/base.py
mediaflow_proxy/extractors/dlhd.py
mediaflow_proxy/extractors/doodstream.py
mediaflow_proxy/extractors/factory.py
mediaflow_proxy/extractors/fastream.py
mediaflow_proxy/extractors/filelions.py
mediaflow_proxy/extractors/filemoon.py
mediaflow_proxy/extractors/livetv.py
mediaflow_proxy/extractors/lulustream.py
mediaflow_proxy/extractors/maxstream.py
mediaflow_proxy/extractors/mixdrop.py
mediaflow_proxy/extractors/okru.py
mediaflow_proxy/extractors/sportsonline.py
mediaflow_proxy/extractors/streamtape.py
mediaflow_proxy/extractors/streamwish.py
mediaflow_proxy/extractors/supervideo.py
mediaflow_proxy/extractors/turbovidplay.py
mediaflow_proxy/extractors/uqload.py
mediaflow_proxy/extractors/vavoo.py
mediaflow_proxy/extractors/vidmoly.py
mediaflow_proxy/extractors/vidoza.py
mediaflow_proxy/extractors/vixcloud.py
mediaflow_proxy/extractors/voe.py
mediaflow_proxy/routes/__init__.py
mediaflow_proxy/routes/acestream.py
mediaflow_proxy/routes/extractor.py
mediaflow_proxy/routes/playlist_builder.py
mediaflow_proxy/routes/proxy.py
mediaflow_proxy/routes/speedtest.py
mediaflow_proxy/routes/xtream.py
mediaflow_proxy/speedtest/__init__.py
mediaflow_proxy/speedtest/models.py
mediaflow_proxy/speedtest/service.py
mediaflow_proxy/speedtest/providers/all_debrid.py
mediaflow_proxy/speedtest/providers/base.py
mediaflow_proxy/speedtest/providers/real_debrid.py
mediaflow_proxy/static/index.html
mediaflow_proxy/static/logo.png
mediaflow_proxy/static/playlist_builder.html
mediaflow_proxy/static/speedtest.html
mediaflow_proxy/static/speedtest.js
mediaflow_proxy/static/url_generator.html
mediaflow_proxy-2.4.1.dist-info/METADATA
mediaflow_proxy-2.4.1.dist-info/WHEEL
mediaflow_proxy-2.4.1.dist-info/entry_points.txt
mediaflow_proxy-2.4.1.dist-info/licenses/LICENSE
mediaflow_proxy-2.4.1.dist-info/RECORD
