Metadata-Version: 2.4
Name: mediaflow-proxy
Version: 2.4.1
Summary: A high-performance proxy server for streaming media, supporting HTTP(S), HLS, and MPEG-DASH with real-time DRM decryption.
Project-URL: Homepage, https://github.com/mhdzumair/mediaflow-proxy
Project-URL: Repository, https://github.com/mhdzumair/mediaflow-proxy
Project-URL: Documentation, https://github.com/mhdzumair/mediaflow-proxy#readme
Author-email: mhdzumair <mhdzumair@gmail.com>
License: MIT
License-File: LICENSE
Keywords: dash,drm,hls,media,proxy,streaming
Classifier: Development Status :: 4 - Beta
Classifier: Intended Audience :: Developers
Classifier: License :: OSI Approved :: MIT License
Classifier: Programming Language :: Python :: 3
Classifier: Programming Language :: Python :: 3.9
Classifier: Programming Language :: Python :: 3.10
Classifier: Programming Language :: Python :: 3.11
Classifier: Programming Language :: Python :: 3.12
Classifier: Programming Language :: Python :: 3.13
Requires-Python: >=3.9
Requires-Dist: aiofiles
Requires-Dist: aiohttp-socks>=0.8.0
Requires-Dist: aiohttp>=3.9.0
Requires-Dist: beautifulsoup4
Requires-Dist: fastapi
Requires-Dist: gunicorn
Requires-Dist: lxml
Requires-Dist: psutil
Requires-Dist: pycryptodome
Requires-Dist: pydantic-settings
Requires-Dist: tenacity
Requires-Dist: tqdm
Requires-Dist: uvicorn
Requires-Dist: xmltodict
